{
  "indexes": [
    {
      "collectionGroup": "inbox",
      "queryScope": "COLLECTION",
      "fields": [
        { "fieldPath": "read", "order": "ASCENDING" },
        { "fieldPath": "createdAt", "order": "DESCENDING" }
      ]
    },
    {
      "collectionGroup": "inbox",
      "queryScope": "COLLECTION_GROUP",
      "fields": [
        { "fieldPath": "meta.groupId", "order": "ASCENDING" },
        { "fieldPath": "actionStatus", "order": "ASCENDING" }
      ]
    }
  ],
  "fieldOverrides": []
}
